peakrdl_docx/__about__.py
peakrdl_docx/__init__.py
peakrdl_docx/__peakrdl__.py
peakrdl_docx/exporter.py
peakrdl_docx/md2commands.py
peakrdl_docx-0.4.7.dist-info/METADATA
peakrdl_docx-0.4.7.dist-info/WHEEL
peakrdl_docx-0.4.7.dist-info/entry_points.txt
peakrdl_docx-0.4.7.dist-info/top_level.txt
peakrdl_docx-0.4.7.dist-info/RECORD
