Metadata-Version: 2.1
Name: peakrdl-docx
Version: 0.4.7
Summary: Compile SystemRDL definition into a Docx (MsWord) document
Author: Alex Nijmeijer
Project-URL: Repository, https://github.com/nijmeijer/PeakRDL-docx
Project-URL: Tracker, https://github.com/nijmeijer/PeakRDL-docx/issues
Project-URL: Changelog, https://github.com/nijmeijer/PeakRDL-docx/commits/main/
Project-URL: Documentation, https://github.com/nijmeijer/PeakRDL-docx/blob/main/README.md
Keywords: SystemRDL,PeakRDL,CSR,compiler,tool,documentation,generator,Verilog,SystemVerilog,register abstraction layer,FPGA,ASIC
Classifier: Development Status :: 4 - Beta
Classifier: Programming Language :: Python :: 3 :: Only
Classifier: Intended Audience :: Developers
Classifier: License :: OSI Approved :: GNU General Public License v3 (GPLv3)
Classifier: Operating System :: OS Independent
Classifier: Topic :: Scientific/Engineering :: Electronic Design Automation (EDA)
Requires-Python: >=3.10
Requires-Dist: systemrdl-compiler >=1.27.0
Requires-Dist: peakrdl
Requires-Dist: pyquery >=2.0.0
Requires-Dist: python-docx >=1.1.2
